{"id": "_pytest.capture", "path": "/home/test/Desktop/scrapyio/venv/lib/python3.11/site-packages/_pytest/capture.py", "mtime": 1680333696, "size": 33062, "hash": "2b27bd5dbeab1716f5d3d39a9e7eb9016c9d23fb0d7a2ca02f354c02eddbb471", "data_mtime": 1680325188, "dependencies": ["_pytest.config.argparsing", "_pytest.compat", "_pytest.config", "_pytest.deprecated", "_pytest.fixtures", "_pytest.nodes", "contextlib", "functools", "io", "os", "sys", "tempfile", "typing", "typing_extensions", "builtins", "_pytest.main", "_pytest.mark", "_typeshed", "abc", "argparse", "array", "ctypes", "mmap", "pathlib", "pickle", "types"], "suppressed": [], "options": {"disallow_untyped_calls": false, "implicit_optional": false, "warn_return_any": true, "warn_no_return": false, "plugins": [], "disallow_untyped_defs": false, "strict_optional": true, "disable_bytearray_promotion": false, "disabled_error_codes": [], "enabled_error_codes": [], "disallow_incomplete_defs": false, "disallow_untyped_decorators": false, "allow_untyped_globals": false, "disallow_any_expr": false, "disallow_any_generics": false, "warn_unreachable": false, "always_false": [], "follow_imports": "normal", "enable_error_code": [], "strict_equality": false, "allow_redefinition": false, "disable_memoryview_promotion": false, "mypyc": false, "disallow_any_unimported": false, "ignore_errors": false, "bazel": false, "strict_concatenate": false, "disallow_any_decorated": false, "implicit_reexport": true, "warn_unused_ignores": false, "ignore_missing_imports": false, "disallow_any_explicit": false, "disable_error_code": [], "follow_imports_for_stubs": false, "local_partial_types": false, "disallow_subclassing_any": false, "always_true": [], "platform": "linux", "check_untyped_defs": false}, "dep_prios": [5, 5, 5, 5, 5, 5, 10, 10, 5, 10, 10, 5, 5, 25, 5, 30, 30, 30, 30, 30, 30, 30, 30, 30, 30, 30], "dep_lines": [23, 20, 21, 24, 25, 27, 2, 3, 4, 5, 6, 8, 9, 32, 1, 1, 1, 1, 1, 1, 1, 1, 1, 1, 1, 1], "interface_hash": "329968b4aa7dfedc1e30e981a9b1d820e4fb037842ff9072c4cffcb7c252f410", "version_id": "1.1.1", "ignore_all": true, "plugin_data": null}